LICENSE
README.md
setup.py
DeepCell_Spots.egg-info/PKG-INFO
DeepCell_Spots.egg-info/SOURCES.txt
DeepCell_Spots.egg-info/dependency_links.txt
DeepCell_Spots.egg-info/requires.txt
DeepCell_Spots.egg-info/top_level.txt
deepcell_spots/__init__.py
deepcell_spots/_version.py
deepcell_spots/cluster_vis.py
deepcell_spots/cluster_vis_test.py
deepcell_spots/decoding_functions.py
deepcell_spots/decoding_functions_test.py
deepcell_spots/dotnet.py
deepcell_spots/dotnet_losses.py
deepcell_spots/dotnet_losses_test.py
deepcell_spots/dotnet_test.py
deepcell_spots/image_alignment.py
deepcell_spots/image_alignment_test.py
deepcell_spots/image_generators.py
deepcell_spots/image_generators_test.py
deepcell_spots/multiplex.py
deepcell_spots/multiplex_test.py
deepcell_spots/point_metrics.py
deepcell_spots/point_metrics_test.py
deepcell_spots/simulate_data.py
deepcell_spots/simulate_data_test.py
deepcell_spots/singleplex.py
deepcell_spots/singleplex_test.py
deepcell_spots/spot_em.py
deepcell_spots/spot_em_test.py
deepcell_spots/training.py
deepcell_spots/applications/__init__.py
deepcell_spots/applications/polaris.py
deepcell_spots/applications/polaris_test.py
deepcell_spots/applications/spot_decoding.py
deepcell_spots/applications/spot_decoding_test.py
deepcell_spots/applications/spot_detection.py
deepcell_spots/applications/spot_detection_test.py
deepcell_spots/utils/__init__.py
deepcell_spots/utils/augmentation_utils.py
deepcell_spots/utils/augmentation_utils_test.py
deepcell_spots/utils/data_utils.py
deepcell_spots/utils/data_utils_test.py
deepcell_spots/utils/postprocessing_utils.py
deepcell_spots/utils/postprocessing_utils_test.py
deepcell_spots/utils/preprocessing_utils.py
deepcell_spots/utils/preprocessing_utils_test.py
deepcell_spots/utils/results_utils.py
deepcell_spots/utils/results_utils_test.py