Metadata-Version: 2.1
Name: DeepCell-Spots
Version: 0.4.2
Summary: Deep learning for fluorescent spot detection
Home-page: https://github.com/vanvalenlab/deepcell-spots
Download-URL: https://github.com/vanvalenlab/deepcell-spots/tarball/0.4.2
Author: The Van Valen Lab
Author-email: vanvalen@caltech.edu
License: LICENSE
Classifier: Intended Audience :: Developers
Classifier: Intended Audience :: Science/Research
Classifier: Operating System :: OS Independent
Classifier: Programming Language :: Python
Classifier: Programming Language :: Python :: 3
Classifier: Programming Language :: Python :: 3.7
Classifier: Programming Language :: Python :: 3.8
Classifier: Programming Language :: Python :: 3.9
Classifier: Topic :: Scientific/Engineering
Classifier: Topic :: Scientific/Engineering :: Artificial Intelligence
Classifier: Topic :: Scientific/Engineering :: Bio-Informatics
Classifier: Topic :: Scientific/Engineering :: Image Processing
Classifier: Topic :: Scientific/Engineering :: Image Recognition
Classifier: Topic :: Software Development :: Libraries
Classifier: Topic :: Software Development :: Libraries :: Python Modules
Requires-Python: >=3.7, <3.11
Provides-Extra: tests
License-File: LICENSE
